{
  "checkpoint_id": "5e881b35-2882-49a5-a1f5-f6e5540f6898",
  "session_id": "7a721c81-fd28-43c4-99af-2e0f3c8d25d2",
  "checkpoint_type": "chapter_start",
  "chapter_number": 2,
  "step_name": "analyzing_chapters",
  "sequence_number": 5,
  "created_at": "2025-10-02T13:38:21.566040",
  "checkpoint_data": {
    "chapter_number": 2,
    "chapter_title": "Portobello Road",
    "chapter_word_count": 3461,
    "analysis_started": true
  },
  "processing_state": {},
  "generated_prompts": [],
  "emotional_moments_data": [],
  "next_action": "analyze_chapter_content",
  "images_generated_count": 0,
  "total_images_at_checkpoint": 0,
  "progress_percent": 25
}